ecs_consul_reg/__init__.py
ecs_consul_reg/main.py
ecs_consul_reg-0.1.3.dist-info/METADATA
ecs_consul_reg-0.1.3.dist-info/RECORD
ecs_consul_reg-0.1.3.dist-info/WHEEL
ecs_consul_reg-0.1.3.dist-info/entry_points.txt
ecs_consul_reg-0.1.3.dist-info/top_level.txt
